setup.cfg
setup.py
activedetect/__init__.py
activedetect.egg-info/PKG-INFO
activedetect.egg-info/SOURCES.txt
activedetect.egg-info/dependency_links.txt
activedetect.egg-info/requires.txt
activedetect.egg-info/top_level.txt
activedetect/error_detectors/DistributionErrorModule.py
activedetect/error_detectors/ErrorDetector.py
activedetect/error_detectors/ErrorModule.py
activedetect/error_detectors/QuantitativeErrorModule.py
activedetect/error_detectors/SemanticErrorModule.py
activedetect/error_detectors/StringSimilarityErrorModule.py
activedetect/error_detectors/__init__.py
activedetect/loaders/__init__.py
activedetect/loaders/csv_loader.py
activedetect/loaders/type_inference.py
activedetect/model_based/HardFilter.py
activedetect/model_based/SafeSetFilter.py
activedetect/model_based/__init__.py
activedetect/model_based/model_eval_utils.py
activedetect/model_based/preprocessing_utils.py
activedetect/reporting/CSVLogging.py
activedetect/reporting/Logging.py
activedetect/reporting/__init__.py
test/test_loaders.py