Metadata-Version: 1.1
Name: activedetect
Version: 0.1.3
Summary: A Library For Error Detection For Predictive Analytics
Home-page: https://github.com/sjyk/activedetect/
Author: Sanjay Krishnan and Eugene Wu
Author-email: sanjay@eecs.berkeley.edu
License: UNKNOWN
Download-URL: https://github.com/sjyk/activedetect/tarball/0.1.3
Keywords: error,detection,cleaning
Platform: UNKNOWN
